{
  "updated": "2026-05-22T02:41:10.005019+00:00",
  "challengers": [
    {
      "id": "challenger_2026-05-22_0",
      "slot": "daily",
      "tag": "בטיחות בסביבה הביתית",
      "tag_color": "te",
      "question": "האם לחייב ולסבסד התקנת סורגים או רשתות בטיחות בכל דירה בבניין רב-קומות",
      "context": "בכל שנה מגיעים למיון כ-15 ילדים עקב נפילה מחלון או מרפסת (נתוני ארגון בטרם)",
      "cost_note": {
        "line1": "עלות סבסוד של 50% להתקנה: כ-150 מיליון ש״ח בשנה",
        "line2": "יחול על בניינים מעל 3 קומות, כ-200 אלף משקי בית",
        "line3": "ללא סבסוד, האחריות והעלות נשארות במלואן על ההורים"
      },
      "trade_off_axis": "תקציב מדינה לבטיחות פרטית מול אחריות הורית",
      "vote_count": 124500,
      "info": {
        "title": "סבסוד אמצעי בטיחות בחלונות",
        "subtitle": "מניעת אסונות בסביבה הביתית",
        "perspectives": [
          {
            "if_label": "אם הסכמתם — אולי כי...",
            "detail": "התקנת סורגים מורידה את סיכוי הנפילה ב-<strong>95%</strong>, וסבסוד ינגיש זאת למשפחות מעוטות יכולת",
            "source": "ארגון בטרם"
          },
          {
            "if_label": "אם הסכמתם — אולי כי...",
            "detail": "אסדרה ממשלתית תחייב קבלנים לשלב אמצעי בטיחות כבר בשלב הבנייה, מה שיוזיל עלויות לטווח ארוך",
            "source": "משרד הבינוי והשיכון"
          },
          {
            "if_label": "אם לא הסכמתם — אולי כי...",
            "detail": "הקצאת <strong>150 מיליון ש״ח</strong> לבטיחות פרטית תבוא על חשבון תקציבי רווחה, כשהאחריות צריכה להיות של ההורים",
            "source": "משרד האוצר"
          }
        ]
      },
      "source": "Beterem - Safe Kids Israel",
      "data_tier": "VERIFIED",
      "category": "social",
      "topic_key": "civilian_security_and_public_safety",
      "generated_from": "grok+gemini_2026-05-22",
      "traffic_pct": 0.2,
      "impressions": 0,
      "swipe_completion": null,
      "created": "2026-05-22T02:41:10.005019+00:00"
    },
    {
      "id": "challenger_2026-05-22_1",
      "slot": "daily",
      "tag": "תשתיות ובטיחות בדרכים",
      "tag_color": "co",
      "question": "האם להעלות את אגרת הנסיעה בכביש 6 כדי לממן צוותי חילוץ והצלה ייעודיים לאורך הציר",
      "context": "זמן ההגעה הממוצע של כוחות הצלה לתאונות בכבישים מהירים עומד על כ-12 דקות (נתוני הרלב\"ד)",
      "cost_note": {
        "line1": "תוספת של כ-2 ש״ח לכל מקטע נסיעה בכביש האגרה",
        "line2": "מימון 5 תחנות הזנקה חדשות לאורך כביש 6",
        "line3": "ללא התוספת, זמני ההגעה ימשיכו להיות תלויים בעומסי התנועה"
      },
      "trade_off_axis": "ייקור אגרות נסיעה מול קיצור זמני תגובה בהצלת חיים",
      "vote_count": 189200,
      "info": {
        "title": "צוותי חילוץ ייעודיים בכבישי אגרה",
        "subtitle": "קיצור זמני התגובה בתאונות דרכים קשות",
        "perspectives": [
          {
            "if_label": "אם הסכמתם — אולי כי...",
            "detail": "קיצור זמן ההגעה ב-<strong>5 דקות</strong> בלבד מעלה את סיכויי ההישרדות של פצועים קשה ב-20%",
            "source": "מד\"א"
          },
          {
            "if_label": "אם הסכמתם — אולי כי...",
            "detail": "כביש אגרה פרטי צריך לספק מעטפת בטיחות מלאה, כולל שירותי חירום זמינים ומיידיים",
            "source": "עמותת אור ירוק"
          },
          {
            "if_label": "אם לא הסכמתם — אולי כי...",
            "detail": "העלאת האגרה תייקר את הנסיעה ב-<strong>מאות שקלים בשנה</strong> לנהג, ותגלגל את אחריות המדינה לכיס האזרח",
            "source": "משרד התחבורה"
          }
        ]
      },
      "source": "National Road Safety Authority (RSA)",
      "data_tier": "VERIFIED",
      "category": "governance",
      "topic_key": "road_and_traffic_safety",
      "generated_from": "grok+gemini_2026-05-22",
      "traffic_pct": 0.2,
      "impressions": 0,
      "swipe_completion": null,
      "created": "2026-05-22T02:41:10.005019+00:00"
    },
    {
      "id": "challenger_2026-05-22_2",
      "slot": "daily",
      "tag": "שירותי חירום רפואיים",
      "tag_color": "bl",
      "question": "האם להעביר תקציב ממרפאות הקהילה לטובת הרחבת צי ניידות הטיפול הנמרץ בערים הגדולות",
      "context": "בישראל פועלות כ-400 ניידות טיפול נמרץ, אך בערים צפופות חסרים צוותים לכיסוי מלא (משרד הבריאות)",
      "cost_note": {
        "line1": "עלות הפעלת ניידת טיפול נמרץ: כ-3 מיליון ש״ח בשנה",
        "line2": "הוספת 50 ניידות תדרוש קיצוץ של כ-150 מיליון ש״ח ממרפאות",
        "line3": "ללא שינוי, העומס על צוותי החירום הקיימים ימשיך לגדול"
      },
      "trade_off_axis": "תקציב רפואה מונעת בקהילה מול רפואת חירום והצלת חיים",
      "vote_count": 210500,
      "info": {
        "title": "תעדוף תקציבי ברפואת חירום",
        "subtitle": "הרחבת מערך הטיפול הנמרץ על חשבון רפואת קהילה",
        "perspectives": [
          {
            "if_label": "אם הסכמתם — אולי כי...",
            "detail": "תוספת של <strong>50 ניידות</strong> תקצר את זמן ההגעה למקרי חירום קריטיים, כמו החייאת תינוקות, מתחת ל-8 דקות",
            "source": "מד\"א"
          },
          {
            "if_label": "אם הסכמתם — אולי כי...",
            "detail": "בערים צפופות כמו ירושלים, זמינות מיידית של רופא ופרמדיק בשטח היא ההבדל בין חיים למוות",
            "source": "ההסתדרות הרפואית"
          },
          {
            "if_label": "אם לא הסכמתם — אולי כי...",
            "detail": "קיצוץ של <strong>150 מיליון ש״ח</strong> ממרפאות הקהילה יפגע ברפואה המונעת ויאריך את התורים לרופאים מומחים",
            "source": "קופות החולים"
          }
        ]
      },
      "source": "Ministry of Health",
      "data_tier": "VERIFIED",
      "category": "health",
      "topic_key": "healthcare_access_and_quality",
      "generated_from": "grok+gemini_2026-05-22",
      "traffic_pct": 0.2,
      "impressions": 0,
      "swipe_completion": null,
      "created": "2026-05-22T02:41:10.005019+00:00"
    },
    {
      "id": "challenger_2026-05-22_3",
      "slot": "daily",
      "tag": "ביטחון אישי ביישובים",
      "tag_color": "pu",
      "question": "האם לממן כיתות כוננות חמושות ביישובים בחברה הערבית על חשבון תקציב השיטור הקהילתי הארצי",
      "context": "מתחילת השנה נפגעו עשרות צעירים באירועי אלימות קשים ביישובי החברה הערבית (יוזמות אברהם)",
      "cost_note": {
        "line1": "הקצאת כ-200 מיליון ש״ח להקמת והכשרת כיתות כוננות",
        "line2": "יפחית כ-20% מתקציב תוכניות השיטור הקהילתי בכלל הארץ",
        "line3": "לחלופין, הישענות על כוחות המשטרה הקיימים שסובלים מעומס"
      },
      "trade_off_axis": "תקציב שיטור קהילתי ארצי מול מענה ביטחוני חמוש ומקומי",
      "vote_count": 156000,
      "info": {
        "title": "כיתות כוננות בחברה הערבית",
        "subtitle": "התמודדות עם הפשיעה והאלימות ברמה המקומית",
        "perspectives": [
          {
            "if_label": "אם הסכמתם — אולי כי...",
            "detail": "נוכחות של כוח מקומי חמוש ומיומן יכולה לצמצם את זמני התגובה לאירועי ירי ב-<strong>60%</strong>",
            "source": "ועד ראשי הרשויות הערביות"
          },
          {
            "if_label": "אם הסכמתם — אולי כי...",
            "detail": "הקמת כיתות כוננות תגביר את תחושת הביטחון האישי ותייצר הרתעה מיידית מול גורמי פשיעה מקומיים",
            "source": "המשרד לביטחון לאומי"
          },
          {
            "if_label": "אם לא הסכמתם — אולי כי...",
            "detail": "קיצוץ של <strong>200 מיליון ש״ח</strong> משיטור קהילתי יפגע במניעת פשיעה ארוכת טווח ובקשר בין המשטרה לאזרחים",
            "source": "משטרת ישראל"
          }
        ]
      },
      "source": "The Abraham Initiatives",
      "data_tier": "VERIFIED",
      "category": "security",
      "topic_key": "civilian_security_and_public_safety",
      "generated_from": "grok+gemini_2026-05-22",
      "traffic_pct": 0.2,
      "impressions": 0,
      "swipe_completion": null,
      "created": "2026-05-22T02:41:10.005019+00:00"
    }
  ]
}